netshow/__init__.py
netshow/app.py
netshow/cli.py
netshow/detail_screen.py
netshow/helpers.py
netshow/styles.py
netshow/types_and_constants.py
netshow-0.2.2.dist-info/METADATA
netshow-0.2.2.dist-info/WHEEL
netshow-0.2.2.dist-info/entry_points.txt
netshow-0.2.2.dist-info/licenses/LICENSE
netshow-0.2.2.dist-info/RECORD
